Topsis_Ranking/topsis.py
TOPSIS_Akriti_101803608-1.0.3.dist-info/LICENSE
TOPSIS_Akriti_101803608-1.0.3.dist-info/METADATA
TOPSIS_Akriti_101803608-1.0.3.dist-info/WHEEL
TOPSIS_Akriti_101803608-1.0.3.dist-info/entry_points.txt
TOPSIS_Akriti_101803608-1.0.3.dist-info/top_level.txt
TOPSIS_Akriti_101803608-1.0.3.dist-info/RECORD
