Metadata-Version: 2.1
Name: TOPSIS-Akriti-101803608
Version: 1.0.3
Summary: A Python package to get best alternative available using TOPSIS method.
Home-page: https://github.com/Akriti0100/TOPSIS-Akriti-101803608
Author: Akriti Singhal
Author-email: akritisinghal1663@gmail.com
License: MIT
Platform: UNKNOWN
Classifier: Development Status :: 3 - Alpha
Classifier: Intended Audience :: Developers
Classifier: License :: OSI Approved :: MIT License
Classifier: Programming Language :: Python :: 3
Classifier: Programming Language :: Python :: 3.8
Requires-Dist: pandas
